LICENSE
README.md
psyker/Cursor.py
psyker/Db.py
psyker/Model.py
psyker/ModelFactory.py
psyker/Psyker.py
psyker/Query.py
psyker/Sql.py
psyker/Table.py
psyker/__init__.py
psyker/columns/Column.py
psyker/columns/Foreign.py
psyker/columns/__init__.py
psyker/exceptions/ConnectionError.py
psyker/exceptions/FieldTypeError.py
psyker/exceptions/__init__.py
psyker-0.1.8.dist-info/LICENSE
psyker-0.1.8.dist-info/WHEEL
psyker-0.1.8.dist-info/METADATA
psyker-0.1.8.dist-info/RECORD
