Metadata-Version: 2.1
Name: psyker
Version: 0.1.8
Summary: A psycopg2 library
Home-page: https://github.com/strangemachines/psyker
License: MPL-2.0
Author: Jacopo Cascioli
Author-email: jacopo@jacopocascioli.com
Requires-Python: >=3.6,<4.0
Classifier: License :: OSI Approved
Classifier: Programming Language :: Python :: 3
Classifier: Programming Language :: Python :: 3.6
Classifier: Programming Language :: Python :: 3.7
Requires-Dist: psycopg2-binary (>=2,<3)
Project-URL: Repository, https://github.com/strangemachines/psyker
